copydoc.py
copydoc-1.0.9.dist-info/METADATA
copydoc-1.0.9.dist-info/RECORD
copydoc-1.0.9.dist-info/WHEEL
copydoc-1.0.9.dist-info/top_level.txt
