Metadata-Version: 2.1
Name: copydoc
Version: 1.0.9
Summary: Parse Google docs for use in content management
Home-page: https://github.com/nprapps/copydoc/
Author: NPR Visuals
Author-email: nprapps@npr.org
License: MIT License
Keywords: google gdocs
Platform: UNKNOWN
Classifier: Development Status :: 5 - Production/Stable
Classifier: Intended Audience :: Developers
Classifier: License :: OSI Approved :: MIT License
Classifier: Topic :: Software Development :: Libraries :: Python Modules
Classifier: Programming Language :: Python
Classifier: Programming Language :: Python :: 2
Classifier: Programming Language :: Python :: 2.7
Classifier: Programming Language :: Python :: 3
Classifier: Programming Language :: Python :: 3.5
Classifier: Programming Language :: Python :: 3.6
Provides-Extra: dev
Requires-Dist: beautifulsoup4 (==4.4.1)
Provides-Extra: dev
Requires-Dist: Sphinx (==1.5.6); extra == 'dev'
Requires-Dist: nose2 (==0.5.0); extra == 'dev'
Requires-Dist: tox (==2.3.1); extra == 'dev'
Requires-Dist: flake8 (==3.5.0); extra == 'dev'
